{
  "schemaVersion": 1,
  "id": "grimac-mc1171",
  "version": "${version}",
  "name": "GrimAC for 1.17+ built against 1.17.1",
  "description": "Libre simulation anticheat designed for 1.21 with 1.8-1.21 support, powered by PacketEvents 2.0.",
  "authors": [
    "GrimAC"
  ],
  "license": "GPLv3",
  "environment": "server",
  "entrypoints": {
    "grimMainLoad": [
      "ac.grim.grimac.platform.fabric.mc1171.GrimACFabric1170LoaderPlugin"
    ]
  },
  "accessWidener": "grimac.accesswidener",
  "depends": {
    "minecraft": ">=1.17",
    "fabric-lifecycle-events-v1": "*"
  }
}
